mamasight/__init__.py
mamasight/screen_parser.py
mamasight/utils.py
mamasight/version.py
mamasight-0.1.1.dist-info/LICENSE
mamasight-0.1.1.dist-info/METADATA
mamasight-0.1.1.dist-info/WHEEL
mamasight-0.1.1.dist-info/top_level.txt
mamasight-0.1.1.dist-info/RECORD
