Metadata-Version: 2.2
Name: mamasight
Version: 0.1.1
Summary: A utility for screen parsing and analysis using YOLO and OCR
Home-page: https://github.com/yourusername/mamasight
Author: Your Name
Author-email: your.email@example.com
Project-URL: Bug Tracker, https://github.com/yourusername/mamasight/issues
Classifier: Programming Language :: Python :: 3
Classifier: License :: OSI Approved :: MIT License
Classifier: Operating System :: OS Independent
Requires-Python: >=3.7
License-File: LICENSE
Requires-Dist: torch>=1.7.0
Requires-Dist: torchvision>=0.8.1
Requires-Dist: ultralytics==8.3.70
Requires-Dist: numpy==1.26.4
Requires-Dist: opencv-python
Requires-Dist: opencv-python-headless
Requires-Dist: paddlepaddle
Requires-Dist: paddleocr
Requires-Dist: easyocr
Requires-Dist: pandas
Requires-Dist: pillow
Requires-Dist: requests
Requires-Dist: huggingface_hub>=0.13.0
Dynamic: author
Dynamic: author-email
Dynamic: classifier
Dynamic: description
Dynamic: description-content-type
Dynamic: home-page
Dynamic: project-url
Dynamic: requires-dist
Dynamic: requires-python
Dynamic: summary
